omero_ark/__init__.py
omero_ark/api/schema.py
omero_ark/builders.py
omero_ark/deployed.py
omero_ark/deployments/test/configs/omero_ark.yaml
omero_ark/deployments/test/docker-compose.yml
omero_ark/deployments/test/public_key.pem
omero_ark/funcs.py
omero_ark/omero_ark.py
omero_ark/rath.py
omero_ark/structures.py
omero_ark/traits.py
omero_ark-0.0.4.dist-info/METADATA
omero_ark-0.0.4.dist-info/WHEEL
omero_ark-0.0.4.dist-info/RECORD
