Metadata-Version: 2.1
Name: omero-ark
Version: 0.0.4
Summary: omero images, but graphql
License: CC BY-NC 3.0
Author: jhnnsrs
Author-email: jhnnsrs@gmail.com
Requires-Python: >=3.8,<4.0
Classifier: License :: Other/Proprietary License
Classifier: Programming Language :: Python :: 3
Classifier: Programming Language :: Python :: 3.8
Classifier: Programming Language :: Python :: 3.9
Classifier: Programming Language :: Python :: 3.10
Classifier: Programming Language :: Python :: 3.11
Provides-Extra: turms
Requires-Dist: dokker (>=0.1.19)
Requires-Dist: rath (>=0.5.0)
